django_presto_templates-0.7.1.dist-info/DESCRIPTION.rst
django_presto_templates-0.7.1.dist-info/METADATA
django_presto_templates-0.7.1.dist-info/RECORD
django_presto_templates-0.7.1.dist-info/WHEEL
django_presto_templates-0.7.1.dist-info/metadata.json
django_presto_templates-0.7.1.dist-info/top_level.txt
presto/__init__.py
presto/test.py
presto/management/__init__.py
presto/management/commands/__init__.py
presto/management/commands/test_presto.py
presto/static/__init__.py
presto/static/presto/__init__.py
presto/static/presto/css/__init__.py
presto/static/presto/fonts/__init__.py
presto/static/presto/images/__init__.py
presto/templates/__init__.py
presto/templates/presto/__init__.py
