Metadata-Version: 2.0
Name: django-presto-templates
Version: 0.7.1
Summary: A collection of pretty, extendable Django templates
Home-page: http://www.roberttownley.com
Author: Robert Townley
Author-email: me@roberttownley.com
License: MIT
Keywords: django presto templates
Platform: UNKNOWN
Classifier: Development Status :: 3 - Alpha
Classifier: Intended Audience :: Developers
Classifier: License :: OSI Approved :: MIT License
Classifier: Programming Language :: Python :: 3
Classifier: Programming Language :: Python :: 3.3
Classifier: Programming Language :: Python :: 3.4
Classifier: Programming Language :: Python :: 3.5
